prometheus_flask_exporter/__init__.py
prometheus_flask_exporter/multiprocess.py
prometheus_flask_exporter-0.23.1.dist-info/LICENSE
prometheus_flask_exporter-0.23.1.dist-info/METADATA
prometheus_flask_exporter-0.23.1.dist-info/WHEEL
prometheus_flask_exporter-0.23.1.dist-info/top_level.txt
prometheus_flask_exporter-0.23.1.dist-info/RECORD
