Metadata-Version: 2.1
Name: prometheus_flask_exporter
Version: 0.23.1
Summary: Prometheus metrics exporter for Flask
Home-page: https://github.com/rycus86/prometheus_flask_exporter
Download-URL: https://github.com/rycus86/prometheus_flask_exporter/archive/0.23.1.tar.gz
Author: Viktor Adam
Author-email: rycus86@gmail.com
License: MIT
Keywords: prometheus,flask,monitoring,exporter
Classifier: Development Status :: 4 - Beta
Classifier: Intended Audience :: Developers
Classifier: Intended Audience :: System Administrators
Classifier: Topic :: System :: Monitoring
Classifier: License :: OSI Approved :: MIT License
Classifier: Programming Language :: Python :: 3
Classifier: Programming Language :: Python :: 3.8
Classifier: Programming Language :: Python :: 3.9
Classifier: Programming Language :: Python :: 3.10
Classifier: Programming Language :: Python :: 3.11
Classifier: Programming Language :: Python :: 3.12
License-File: LICENSE
Requires-Dist: prometheus_client
Requires-Dist: flask
